odoo/addons/account_invoice_select_bank/LICENSE
odoo/addons/account_invoice_select_bank/README.rst
odoo/addons/account_invoice_select_bank/__init__.py
odoo/addons/account_invoice_select_bank/__manifest__.py
odoo/addons/account_invoice_select_bank/images/screen.png
odoo/addons/account_invoice_select_bank/models/__init__.py
odoo/addons/account_invoice_select_bank/models/account_move.py
odoo/addons/account_invoice_select_bank/static/description/icon.png
odoo/addons/account_invoice_select_bank/static/description/index.html
odoo/addons/account_invoice_select_bank/tests/TEST_INSTRUCTIONS.rst
odoo_addon_account_invoice_select_bank-18.0.1.1.0.dist-info/METADATA
odoo_addon_account_invoice_select_bank-18.0.1.1.0.dist-info/WHEEL
odoo_addon_account_invoice_select_bank-18.0.1.1.0.dist-info/top_level.txt
odoo_addon_account_invoice_select_bank-18.0.1.1.0.dist-info/RECORD
